grib2sail/__init__.py
grib2sail/__main__.py
grib2sail/_version.py
grib2sail/cli.py
grib2sail/downloader.py
grib2sail/downloader_arom.py
grib2sail/logger.py
grib2sail/token.py
grib2sail/variables.py
grib2sail/variables_arom.py
grib2sail-0.2.0.dist-info/licenses/LICENSE
grib2sail-0.2.0.dist-info/METADATA
grib2sail-0.2.0.dist-info/WHEEL
grib2sail-0.2.0.dist-info/top_level.txt
grib2sail-0.2.0.dist-info/RECORD
