Metadata-Version: 2.4
Name: grib2sail
Version: 0.2.0
Summary: Grib files downloader for sailing purposes
Author-email: Chinkara <poubelledechinkara@outlook.com>
License-Expression: GPL-3.0-or-later
Project-URL: Homepage, https://github.com/Ch1nkara/GRIB2Sail
Requires-Python: >=3.10
License-File: LICENSE
Requires-Dist: rich
Requires-Dist: keyring
Requires-Dist: typer
Requires-Dist: requests
Dynamic: license-file
